alluxio/__init__.py
alluxio/alluxio_file_system.py
alluxio/const.py
alluxio/worker_ring.py
alluxio-1.0.0.dist-info/LICENSE
alluxio-1.0.0.dist-info/METADATA
alluxio-1.0.0.dist-info/WHEEL
alluxio-1.0.0.dist-info/top_level.txt
alluxio-1.0.0.dist-info/RECORD
