Metadata-Version: 2.1
Name: alluxio
Version: 1.0.0
Summary: Alluxio Python library 1.0.0 provides API to interact with Alluxio servers.
Home-page: https://github.com/Alluxio/alluxio-py
Requires-Python: >=3.8
License-File: LICENSE
Requires-Dist: aiohttp
Requires-Dist: decorator
Requires-Dist: humanfriendly
Requires-Dist: requests
Requires-Dist: etcd3
Requires-Dist: mmh3
Requires-Dist: sortedcontainers
Requires-Dist: protobuf <3.21.0,>=3.20.0
Provides-Extra: tests
Requires-Dist: pytest ; extra == 'tests'
Requires-Dist: pytest-aiohttp ; extra == 'tests'
